zcache/__init__.py
zcache/py.typed
zcache/version.py
zcache/Core/AsyncDatabase.py
zcache/Core/Database.py
zcache/Core/__init__.py
zcache/Extras/AsyncQueue.py
zcache/Extras/AsyncSmartRequest.py
zcache/Extras/Queue.py
zcache/Extras/SmartRequest.py
zcache/Extras/__init__.py
zcache/Interface/__init__.py
zcache/Plugins/AsyncBytesCachePlugins.py
zcache/Plugins/BytesCachePlugins.py
zcache/Plugins/__init__.py
zcache/Storage/AsyncDictStorage.py
zcache/Storage/AsyncFileStorage.py
zcache/Storage/BaseFileStorage.py
zcache/Storage/DictStorage.py
zcache/Storage/FTPStorage.py
zcache/Storage/FcntlStorage.py
zcache/Storage/__init__.py
zcache-3.0.5.dist-info/LICENSE
zcache-3.0.5.dist-info/METADATA
zcache-3.0.5.dist-info/WHEEL
zcache-3.0.5.dist-info/top_level.txt
zcache-3.0.5.dist-info/RECORD
