Metadata-Version: 2.1
Name: zcache
Version: 3.0.5
Summary: Pure typed Python Key Value Database/Cache with abstract storage, plugins and asynchronous support
Home-page: https://github.com/guangrei/zcache
Author: guangrei
Author-email: myawn@pm.me
License: MIT
Keywords: cache key value file json
License-File: LICENSE
Requires-Dist: types-aiofiles
Requires-Dist: aiohttp
Requires-Dist: aiofiles
